{
  "source": "fetch",
  "ts_bj": "2026-05-20 14:38:37",
  "date": "2026-05-20",
  "market": {
    "zt": 57,
    "dt": 21,
    "zab": 16,
    "zab_rate": 21.9,
    "lianban": 9,
    "max_lianban": 6,
    "amount": "26862.47亿"
  },
  "concepts": [
    {
      "name": "机器人概念",
      "lead": "北自科技",
      "chg_pct": null
    },
    {
      "name": "算力",
      "lead": "弘信电子",
      "chg_pct": null
    },
    {
      "name": "芯片",
      "lead": "合肥城建",
      "chg_pct": null
    },
    {
      "name": "ST板块",
      "lead": "*ST准油",
      "chg_pct": null
    },
    {
      "name": "通信",
      "lead": "宝鼎科技",
      "chg_pct": null
    }
  ],
  "alerts": []
}