{"date": "2026-07-01", "generatedAt": "2026-07-01 10:16:02", "relay": [{"name": "еӨҡж°ҹеӨҡ", "code": "002407", "lbc": 3, "hy": "еҢ–еӯҰеҲ¶е“Ғ", "fundYi": 11.2781289, "open": 1, "predTheme": "ж–°жқҗж–ҷ", "predThemeCanonical": "ж–°жқҗж–ҷ", "hasTier": true, "cjeYi": 36.51455952, "qualityLabel": "жё©е’Ңж”ҫйҮҸ", "qualityScore": 84.0, "nextStep": "3иҝӣ4", "stepRate": 0.0, "stepContextScore": 48, "promoEcology": 22, "heightContextScore": 3, "environmentScore": 27, "leaderFactorScore": 86, "relayFactorScore": 66, "capacityFactorScore": 79, "riskControlScore": 37, "breakRisk": 90, "themePersistScore": 73, "leaderPhilosophyScore": 100, "recentHighSignal": {"available": false, "window": 7}, "thsNewhigh": {}, "themeLadderProfile": {"score": 77, "label": "жўҜйҳҹе®Ңж•ҙ", "leaderBoards": 3, "coreCount": 4, "midCarryCount": 3, "followerCount": 7, "frontCount": 4, "gapCount": 0, "isComplete": true, "hasCarry": true, "leaderName": "еӨҡж°ҹеӨҡ"}, "_isRecentHigh7d": false, "_breakoutDoubleConfirm": false, "leaderRole": "driver", "score": 68, "factorScore": 68, "factorBreakdown": {"environment": 27, "market": 39, "themeEnv": 100, "marketGate": -16, "sector": 73, "leader": 86, "relay": 66, "capacity": 79, "risk": 37, "opportunity": 81, "edge": 14, "heightBreakout": 0, "tide": 4}, "factorHint": "зҺҜеўғ27(дј‘жҒҜдјҳе…Ҳ) / жқҝеқ—73 / йҫҷеӨҙ86 / жҺҘеҠӣ66 / е®№йҮҸ79 / йЈҺйҷ©37 / жҪ®жұҗ+4 / жўҜйҳҹ77 / жқЎд»¶и§ҰеҸ‘", "scoreBand": "жқЎд»¶и§ҰеҸ‘", "scoreBandTone": "watch", "superLeaderTone": "", "scoreAction": "йңҖиҰҒи¶…йў„жңҹ", "marketGate": {"score": 27, "label": "дј‘жҒҜдјҳе…Ҳ", "action": "дёҚдё»еҠЁжҺҘеҠӣ"}, "sectorTrendScore": 79, "sectorRankScore": 88, "plateRank": 0, "plateName": "", "plateNameCanonical": "", "tideStatus": "observe_candidate", "tideAction": "watch", "tidePhase": "neutral", "tideCoreScore": 58.0, "tideEbbScore": 39.0, "tideAdjust": 4.0, "tideRelayAdjust": 1.0, "tideRiskAdjust": -4.0, "tideWatchAdjust": 12.0, "tideRelayGate": 3.0, "tideHint": "ж–°жқҗж–ҷжңүи§ӮеҜҹд»·еҖјпјҢзӯүеҫ…жғ…з»Ә/йҮҸиғҪ/ж¶ҲжҒҜз»§з»ӯе…ұжҢҜгҖӮ", "tideCaution": "", "factorLabels": {"environment": "еҒҸејұ", "sector": "еҒҸејә", "leader": "ејә", "relay": "дёӯжҖ§", "capacity": "еҒҸејә", "risk": "еҒҸејұ"}, "tags": [{"text": "3иҝӣ4", "cls": "ladder-chip-strong red-text"}, {"text": "3жқҝ", "cls": "ladder-chip-cool muted-text"}, {"text": "ејәдё»зәҝ", "cls": "ladder-chip-strong red-text"}, {"text": "еүҚйҫҷеӨҙ", "cls": "ladder-chip-strong red-text"}, {"text": "еёҰеҠЁеә·ж¬Јж–°жқҗгҖҒдёңж–№й”Ҷдёҡ", "cls": "ladder-chip-strong red-text"}, {"text": "жҷӢзә§з”ҹжҖҒејұ", "cls": "ladder-chip-warn orange-text"}, {"text": "й«ҳеәҰеҺӢеҲ¶", "cls": "ladder-chip-warn orange-text"}, {"text": "ж–ӯжқҝйЈҺйҷ©й«ҳ", "cls": "ladder-chip-warn orange-text"}, {"text": "1ж¬ЎејҖжқҝ", "cls": "ladder-chip-warn orange-text"}, {"text": "жё©е’Ңж”ҫйҮҸ", "cls": "ladder-chip-cool muted-text"}, {"text": "йҰ–е°Ғ09:31", "cls": "ladder-chip-cool muted-text"}, {"text": "зӘҒз ҙж–°й«ҳ", "cls": "ladder-chip-strong red-text"}, {"text": "йҮҸд»·е…ұжҢҜ", "cls": "ladder-chip-cool muted-text"}, {"text": "йўҳжқҗеҸ‘ж•Ј", "cls": "ladder-chip-cool muted-text"}, {"text": "е°ҒеҚ•11.28дәҝ", "cls": "ladder-chip-cool muted-text"}, {"text": "6.2%жҚўжүӢ", "cls": "ladder-chip-cool muted-text"}, {"text": "жҲҗдәӨйўқ36.51дәҝ", "cls": "ladder-chip-cool muted-text"}, {"text": "еёӮеҖј658дәҝ", "cls": "ladder-chip-cool muted-text"}, {"text": "жўҜйҳҹе®Ңж•ҙ", "cls": "ladder-chip-cool muted-text"}, {"text": "еҫ®еһӢз©ҝи¶Ҡ", "cls": "ladder-chip-cool muted-text"}, {"text": "ж–°жқҗж–ҷ", "cls": "ladder-chip-cool muted-text"}, {"text": "еҚҠеҜјдҪ“", "cls": "ladder-chip-cool muted-text"}, {"text": "е®№йҮҸж ё", "cls": "ladder-chip-warn orange-text"}], "tagRows": [{"tone": "red", "tags": [{"text": "3иҝӣ4", "cls": "ladder-chip-strong red-text"}, {"text": "ејәдё»зәҝ", "cls": "ladder-chip-strong red-text"}, {"text": "еүҚйҫҷеӨҙ", "cls": "ladder-chip-strong red-text"}, {"text": "еёҰеҠЁеә·ж¬Јж–°жқҗгҖҒдёңж–№й”Ҷдёҡ", "cls": "ladder-chip-strong red-text"}, {"text": "зӘҒз ҙж–°й«ҳ", "cls": "ladder-chip-strong red-text"}]}, {"tone": "orange", "tags": [{"text": "жҷӢзә§з”ҹжҖҒејұ", "cls": "ladder-chip-warn orange-text"}, {"text": "й«ҳеәҰеҺӢеҲ¶", "cls": "ladder-chip-warn orange-text"}, {"text": "ж–ӯжқҝйЈҺйҷ©й«ҳ", "cls": "ladder-chip-warn orange-text"}, {"text": "1ж¬ЎејҖжқҝ", "cls": "ladder-chip-warn orange-text"}, {"text": "е®№йҮҸж ё", "cls": "ladder-chip-warn orange-text"}]}, {"tone": "muted", "tags": [{"text": "3жқҝ", "cls": "ladder-chip-cool muted-text"}, {"text": "жё©е’Ңж”ҫйҮҸ", "cls": "ladder-chip-cool muted-text"}, {"text": "йҰ–е°Ғ09:31", "cls": "ladder-chip-cool muted-text"}, {"text": "йҮҸд»·е…ұжҢҜ", "cls": "ladder-chip-cool muted-text"}, {"text": "йўҳжқҗеҸ‘ж•Ј", "cls": "ladder-chip-cool muted-text"}, {"text": "е°ҒеҚ•11.28дәҝ", "cls": "ladder-chip-cool muted-text"}, {"text": "6.2%жҚўжүӢ", "cls": "ladder-chip-cool muted-text"}, {"text": "жҲҗдәӨйўқ36.51дәҝ", "cls": "ladder-chip-cool muted-text"}, {"text": "еёӮеҖј658дәҝ", "cls": "ladder-chip-cool muted-text"}, {"text": "жўҜйҳҹе®Ңж•ҙ", "cls": "ladder-chip-cool muted-text"}, {"text": "еҫ®еһӢз©ҝи¶Ҡ", "cls": "ladder-chip-cool muted-text"}, {"text": "ж–°жқҗж–ҷ", "cls": "ladder-chip-cool muted-text"}, {"text": "еҚҠеҜјдҪ“", "cls": "ladder-chip-cool muted-text"}]}], "capacityLabel": "е®№йҮҸж ё", "reason": "<span class=\"reason-bits\">ж–°жқҗж–ҷйҫҷеӨҙеёҰеҠЁ В· жўҜйҳҹеёҰеҠЁеә·ж¬Јж–°жқҗгҖҒдёңж–№й”Ҷдёҡ В· ејәдё»зәҝ В· зӘҒз ҙж–°й«ҳ(3жқҝ) В· жё©е’Ңж”ҫйҮҸ В· е°ҒеҚ•еҒҸејә В· е°ҒжқҝзЁі В· й«ҳеәҰеҺӢеҲ¶ В· ж–ӯжқҝйЈҺйҷ©й«ҳ</span><div class=\"exp-wrap\"><div class=\"exp-row\"><span class=\"exp-pill pill-pre\">йў„жңҹ</span>е№іејҖпјҲ-1%~+1%%пјү+ з«һд»·йҮҸиғҪвүҘ2.19дәҝ</div><div class=\"exp-row\"><span class=\"exp-pill pill-hi\">и¶…йў„жңҹ</span>й«ҳејҖвүҘ+1%% + з«һд»·йҮҸиғҪвүҘ2.19дәҝ</div><div class=\"exp-row\"><span class=\"exp-pill pill-lo\">дҪҺйў„жңҹ</span>дҪҺдәҺ-1%% жҲ– з«һд»·йҮҸиғҪ<1.53дәҝ</div></div>", "factorRank": 1, "relayRank": 1, "relaySelectionMode": "broad", "scoreLabel": "жҺЁиҚҗеӣ еӯҗ", "scoreSubLabel": "е…ңеә•еҖҷйҖү В· д»…и¶…йў„жңҹ"}, {"name": "жҳҠеҚҺз§‘жҠҖ", "code": "600378", "lbc": 3, "hy": "еҢ–еӯҰеҲ¶е“Ғ", "fundYi": 3.13573174, "open": 1, "predTheme": "еӣҪиө„ж”№йқ©", "predThemeCanonical": "еӣҪиө„ж”№йқ©", "hasTier": true, "cjeYi": 40.27620848, "qualityLabel": "жё©е’Ңж”ҫйҮҸ", "qualityScore": 84.0, "nextStep": "3иҝӣ4", "stepRate": 0.0, "stepContextScore": 48, "promoEcology": 22, "heightContextScore": 3, "environmentScore": 27, "leaderFactorScore": 88, "relayFactorScore": 61, "capacityFactorScore": 73, "riskControlScore": 33, "breakRisk": 90, "themePersistScore": 77, "leaderPhilosophyScore": 100, "recentHighSignal": {"available": false, "window": 7, "currentDate": "2026-06-30", "currentHigh": 75.38, "prevHigh": 73.03, "sampleSize": 5, "isRecentHigh": false, "breakoutPct": 3.22}, "thsNewhigh": {}, "themeLadderProfile": {"score": 76, "label": "жўҜйҳҹе®Ңж•ҙ", "leaderBoards": 3, "coreCount": 6, "midCarryCount": 4, "followerCount": 9, "frontCount": 6, "gapCount": 0, "isComplete": true, "hasCarry": true, "leaderName": "жҳҠеҚҺз§‘жҠҖ"}, "_isRecentHigh7d": false, "_breakoutDoubleConfirm": false, "leaderRole": "driver", "score": 67, "factorScore": 67, "factorBreakdown": {"environment": 27, "market": 39, "themeEnv": 100, "marketGate": -16, "sector": 79, "leader": 88, "relay": 61, "capacity": 73, "risk": 33, "opportunity": 81, "edge": 14, "heightBreakout": 0, "tide": 4}, "factorHint": "зҺҜеўғ27(дј‘жҒҜдјҳе…Ҳ) / жқҝеқ—79 / йҫҷеӨҙ88 / жҺҘеҠӣ61 / е®№йҮҸ73 / йЈҺйҷ©33 / жҪ®жұҗ+4 / жўҜйҳҹ76 / жқЎд»¶и§ҰеҸ‘", "scoreBand": "жқЎд»¶и§ҰеҸ‘", "scoreBandTone": "watch", "superLeaderTone": "", "scoreAction": "йңҖиҰҒи¶…йў„жңҹ", "marketGate": {"score": 27, "label": "дј‘жҒҜдјҳе…Ҳ", "action": "дёҚдё»еҠЁжҺҘеҠӣ"}, "sectorTrendScore": 83, "sectorRankScore": 92, "plateRank": 0, "plateName": "", "plateNameCanonical": "", "tideStatus": "observe_candidate", "tideAction": "watch", "tidePhase": "neutral", "tideCoreScore": 57.0, "tideEbbScore": 39.0, "tideAdjust": 4.0, "tideRelayAdjust": 1.0, "tideRiskAdjust": -4.0, "tideWatchAdjust": 12.0, "tideRelayGate": 3.0, "tideHint": "еӣҪиө„ж”№йқ©жңүи§ӮеҜҹд»·еҖјпјҢзӯүеҫ…жғ…з»Ә/йҮҸиғҪ/ж¶ҲжҒҜз»§з»ӯе…ұжҢҜгҖӮ", "tideCaution": "", "factorLabels": {"environment": "еҒҸејұ", "sector": "еҒҸејә", "leader": "ејә", "relay": "дёӯжҖ§", "capacity": "еҒҸејә", "risk": "еҒҸејұ"}, "tags": [{"text": "3иҝӣ4", "cls": "ladder-chip-strong red-text"}, {"text": "3жқҝ", "cls": "ladder-chip-cool muted-text"}, {"text": "жһҒејәдё»зәҝ", "cls": "ladder-chip-strong red-text"}, {"text": "еүҚйҫҷеӨҙ", "cls": "ladder-chip-strong red-text"}, {"text": "еёҰеҠЁжөҷжұҹдёңж—ҘгҖҒеә·ж¬Јж–°жқҗ", "cls": "ladder-chip-strong red-text"}, {"text": "жҷӢзә§з”ҹжҖҒејұ", "cls": "ladder-chip-warn orange-text"}, {"text": "й«ҳеәҰеҺӢеҲ¶", "cls": "ladder-chip-warn orange-text"}, {"text": "ж–ӯжқҝйЈҺйҷ©й«ҳ", "cls": "ladder-chip-warn orange-text"}, {"text": "1ж¬ЎејҖжқҝ", "cls": "ladder-chip-warn orange-text"}, {"text": "жё©е’Ңж”ҫйҮҸ", "cls": "ladder-chip-cool muted-text"}, {"text": "йҰ–е°Ғ09:52", "cls": "ladder-chip-cool muted-text"}, {"text": "зӘҒз ҙж–°й«ҳ", "cls": "ladder-chip-strong red-text"}, {"text": "йҮҸд»·е…ұжҢҜ", "cls": "ladder-chip-cool muted-text"}, {"text": "йўҳжқҗеҸ‘ж•Ј", "cls": "ladder-chip-cool muted-text"}, {"text": "е°ҒеҚ•3.14дәҝ", "cls": "ladder-chip-cool muted-text"}, {"text": "4.7%жҚўжүӢ", "cls": "ladder-chip-cool muted-text"}, {"text": "жҲҗдәӨйўқ40.28дәҝ", "cls": "ladder-chip-cool muted-text"}, {"text": "еёӮеҖј1070дәҝ", "cls": "ladder-chip-cool muted-text"}, {"text": "жўҜйҳҹе®Ңж•ҙ", "cls": "ladder-chip-cool muted-text"}, {"text": "еҫ®еһӢз©ҝи¶Ҡ", "cls": "ladder-chip-cool muted-text"}, {"text": "еӣҪиө„ж”№йқ©", "cls": "ladder-chip-cool muted-text"}, {"text": "еҚҠеҜјдҪ“", "cls": "ladder-chip-cool muted-text"}, {"text": "е®№йҮҸж ё", "cls": "ladder-chip-warn orange-text"}], "tagRows": [{"tone": "red", "tags": [{"text": "3иҝӣ4", "cls": "ladder-chip-strong red-text"}, {"text": "жһҒејәдё»зәҝ", "cls": "ladder-chip-strong red-text"}, {"text": "еүҚйҫҷеӨҙ", "cls": "ladder-chip-strong red-text"}, {"text": "еёҰеҠЁжөҷжұҹдёңж—ҘгҖҒеә·ж¬Јж–°жқҗ", "cls": "ladder-chip-strong red-text"}, {"text": "зӘҒз ҙж–°й«ҳ", "cls": "ladder-chip-strong red-text"}]}, {"tone": "orange", "tags": [{"text": "жҷӢзә§з”ҹжҖҒејұ", "cls": "ladder-chip-warn orange-text"}, {"text": "й«ҳеәҰеҺӢеҲ¶", "cls": "ladder-chip-warn orange-text"}, {"text": "ж–ӯжқҝйЈҺйҷ©й«ҳ", "cls": "ladder-chip-warn orange-text"}, {"text": "1ж¬ЎејҖжқҝ", "cls": "ladder-chip-warn orange-text"}, {"text": "е®№йҮҸж ё", "cls": "ladder-chip-warn orange-text"}]}, {"tone": "muted", "tags": [{"text": "3жқҝ", "cls": "ladder-chip-cool muted-text"}, {"text": "жё©е’Ңж”ҫйҮҸ", "cls": "ladder-chip-cool muted-text"}, {"text": "йҰ–е°Ғ09:52", "cls": "ladder-chip-cool muted-text"}, {"text": "йҮҸд»·е…ұжҢҜ", "cls": "ladder-chip-cool muted-text"}, {"text": "йўҳжқҗеҸ‘ж•Ј", "cls": "ladder-chip-cool muted-text"}, {"text": "е°ҒеҚ•3.14дәҝ", "cls": "ladder-chip-cool muted-text"}, {"text": "4.7%жҚўжүӢ", "cls": "ladder-chip-cool muted-text"}, {"text": "жҲҗдәӨйўқ40.28дәҝ", "cls": "ladder-chip-cool muted-text"}, {"text": "еёӮеҖј1070дәҝ", "cls": "ladder-chip-cool muted-text"}, {"text": "жўҜйҳҹе®Ңж•ҙ", "cls": "ladder-chip-cool muted-text"}, {"text": "еҫ®еһӢз©ҝи¶Ҡ", "cls": "ladder-chip-cool muted-text"}, {"text": "еӣҪиө„ж”№йқ©", "cls": "ladder-chip-cool muted-text"}, {"text": "еҚҠеҜјдҪ“", "cls": "ladder-chip-cool muted-text"}]}], "capacityLabel": "е®№йҮҸж ё", "reason": "<span class=\"reason-bits\">еӣҪиө„ж”№йқ©йҫҷеӨҙеёҰеҠЁ В· жўҜйҳҹеёҰеҠЁжөҷжұҹдёңж—ҘгҖҒеә·ж¬Јж–°жқҗ В· жһҒејәдё»зәҝ В· зӘҒз ҙж–°й«ҳ(3жқҝ) В· жё©е’Ңж”ҫйҮҸ В· е°ҒжқҝзЁі В· е®№йҮҸеӨҹ В· й«ҳеәҰеҺӢеҲ¶ В· ж–ӯжқҝйЈҺйҷ©й«ҳ</span><div class=\"exp-wrap\"><div class=\"exp-row\"><span class=\"exp-pill pill-pre\">йў„жңҹ</span>е№іејҖпјҲ-1%~+1%%пјү+ з«һд»·йҮҸиғҪвүҘ2.42дәҝ</div><div class=\"exp-row\"><span class=\"exp-pill pill-hi\">и¶…йў„жңҹ</span>й«ҳејҖвүҘ+1%% + з«һд»·йҮҸиғҪвүҘ2.42дәҝ</div><div class=\"exp-row\"><span class=\"exp-pill pill-lo\">дҪҺйў„жңҹ</span>дҪҺдәҺ-1%% жҲ– з«һд»·йҮҸиғҪ<1.69дәҝ</div></div>", "factorRank": 2, "relayRank": 2, "relaySelectionMode": "broad", "scoreLabel": "жҺЁиҚҗеӣ еӯҗ", "scoreSubLabel": "е…ңеә•еҖҷйҖү В· д»…и¶…йў„жңҹ"}], "watch": [{"name": "жөҷжұҹдёңж—Ҙ", "code": "600113", "lbc": 3, "hy": "дёҖиҲ¬йӣ¶е”®", "fundYi": 0.7229555, "open": 7, "predTheme": "еӣҪиө„ж”№йқ©", "predThemeCanonical": "еӣҪиө„ж”№йқ©", "hasTier": true, "cjeYi": 4.48037648, "qualityLabel": "еҸҚеӨҚеӣһе°Ғ", "qualityScore": 54.0, "nextStep": "3иҝӣ4", "stepRate": 0.0, "stepContextScore": 48, "promoEcology": 22, "heightContextScore": 3, "environmentScore": 27, "leaderFactorScore": 74, "relayFactorScore": 47, "capacityFactorScore": 47, "riskControlScore": 9, "breakRisk": 98, "themePersistScore": 77, "leaderPhilosophyScore": 87, "recentHighSignal": {"available": false, "window": 7}, "thsNewhigh": {}, "themeLadderProfile": {"score": 76, "label": "жўҜйҳҹе®Ңж•ҙ", "leaderBoards": 3, "coreCount": 6, "midCarryCount": 4, "followerCount": 9, "frontCount": 6, "gapCount": 0, "isComplete": true, "hasCarry": true, "leaderName": "жҳҠеҚҺз§‘жҠҖ"}, "_isRecentHigh7d": false, "_breakoutDoubleConfirm": false, "leaderRole": "core", "score": 48, "factorScore": 48, "factorBreakdown": {"environment": 27, "market": 39, "themeEnv": 100, "marketGate": -16, "sector": 76, "leader": 74, "relay": 47, "capacity": 47, "risk": 9, "opportunity": 81, "edge": 6, "heightBreakout": 0, "tide": 4}, "factorHint": "зҺҜеўғ27(дј‘жҒҜдјҳе…Ҳ) / жқҝеқ—76 / йҫҷеӨҙ74 / жҺҘеҠӣ47 / е®№йҮҸ47 / йЈҺйҷ©9 / жҪ®жұҗ+4 / жўҜйҳҹ76 / еҸӘи§ӮеҜҹ", "scoreBand": "еҸӘи§ӮеҜҹ", "scoreBandTone": "cool", "superLeaderTone": "", "scoreAction": "дёҚдё»еҠЁжҺҘеҠӣ", "marketGate": {"score": 27, "label": "дј‘жҒҜдјҳе…Ҳ", "action": "дёҚдё»еҠЁжҺҘеҠӣ"}, "sectorTrendScore": 79, "sectorRankScore": 92, "plateRank": 0, "plateName": "", "plateNameCanonical": "", "tideStatus": "observe_candidate", "tideAction": "watch", "tidePhase": "neutral", "tideCoreScore": 57.0, "tideEbbScore": 39.0, "tideAdjust": 4.0, "tideRelayAdjust": 1.0, "tideRiskAdjust": -4.0, "tideWatchAdjust": 12.0, "tideRelayGate": 3.0, "tideHint": "еӣҪиө„ж”№йқ©жңүи§ӮеҜҹд»·еҖјпјҢзӯүеҫ…жғ…з»Ә/йҮҸиғҪ/ж¶ҲжҒҜз»§з»ӯе…ұжҢҜгҖӮ", "tideCaution": "", "factorLabels": {"environment": "еҒҸејұ", "sector": "еҒҸејә", "leader": "еҒҸејә", "relay": "еҒҸејұ", "capacity": "еҒҸејұ", "risk": "еҒҸејұ"}, "tags": [{"text": "3иҝӣ4", "cls": "ladder-chip-strong red-text"}, {"text": "3жқҝ", "cls": "ladder-chip-cool muted-text"}, {"text": "жһҒејәдё»зәҝ", "cls": "ladder-chip-strong red-text"}, {"text": "еүҚйҫҷеӨҙ", "cls": "ladder-chip-strong red-text"}, {"text": "и·ҹйЈҺжҳҠеҚҺз§‘жҠҖ", "cls": "ladder-chip-warn orange-text"}, {"text": "еҸҚеӨҚеӣһе°Ғ", "cls": "ladder-chip-warn orange-text"}, {"text": "жҷӢзә§з”ҹжҖҒејұ", "cls": "ladder-chip-warn orange-text"}, {"text": "й«ҳеәҰеҺӢеҲ¶", "cls": "ladder-chip-warn orange-text"}, {"text": "ж–ӯжқҝйЈҺйҷ©й«ҳ", "cls": "ladder-chip-warn orange-text"}, {"text": "7ж¬ЎејҖжқҝ", "cls": "ladder-chip-warn orange-text"}, {"text": "жё©е’Ңж”ҫйҮҸ", "cls": "ladder-chip-cool muted-text"}, {"text": "йҰ–е°Ғ09:30", "cls": "ladder-chip-cool muted-text"}, {"text": "зӘҒз ҙж–°й«ҳ", "cls": "ladder-chip-strong red-text"}, {"text": "йҮҸд»·е…ұжҢҜ", "cls": "ladder-chip-cool muted-text"}, {"text": "е°ҒеҚ•0.72дәҝ", "cls": "ladder-chip-cool muted-text"}, {"text": "3.0%жҚўжүӢ", "cls": "ladder-chip-cool muted-text"}, {"text": "жҲҗдәӨйўқ4.48дәҝ", "cls": "ladder-chip-cool muted-text"}, {"text": "еёӮеҖј154дәҝ", "cls": "ladder-chip-cool muted-text"}, {"text": "жўҜйҳҹе®Ңж•ҙ", "cls": "ladder-chip-cool muted-text"}, {"text": "еҫ®еһӢз©ҝи¶Ҡ", "cls": "ladder-chip-cool muted-text"}, {"text": "еӣҪиө„ж”№йқ©", "cls": "ladder-chip-cool muted-text"}], "tagRows": [{"tone": "red", "tags": [{"text": "3иҝӣ4", "cls": "ladder-chip-strong red-text"}, {"text": "жһҒејәдё»зәҝ", "cls": "ladder-chip-strong red-text"}, {"text": "еүҚйҫҷеӨҙ", "cls": "ladder-chip-strong red-text"}, {"text": "зӘҒз ҙж–°й«ҳ", "cls": "ladder-chip-strong red-text"}]}, {"tone": "orange", "tags": [{"text": "и·ҹйЈҺжҳҠеҚҺз§‘жҠҖ", "cls": "ladder-chip-warn orange-text"}, {"text": "еҸҚеӨҚеӣһе°Ғ", "cls": "ladder-chip-warn orange-text"}, {"text": "жҷӢзә§з”ҹжҖҒејұ", "cls": "ladder-chip-warn orange-text"}, {"text": "й«ҳеәҰеҺӢеҲ¶", "cls": "ladder-chip-warn orange-text"}, {"text": "ж–ӯжқҝйЈҺйҷ©й«ҳ", "cls": "ladder-chip-warn orange-text"}, {"text": "7ж¬ЎејҖжқҝ", "cls": "ladder-chip-warn orange-text"}]}, {"tone": "muted", "tags": [{"text": "3жқҝ", "cls": "ladder-chip-cool muted-text"}, {"text": "жё©е’Ңж”ҫйҮҸ", "cls": "ladder-chip-cool muted-text"}, {"text": "йҰ–е°Ғ09:30", "cls": "ladder-chip-cool muted-text"}, {"text": "йҮҸд»·е…ұжҢҜ", "cls": "ladder-chip-cool muted-text"}, {"text": "е°ҒеҚ•0.72дәҝ", "cls": "ladder-chip-cool muted-text"}, {"text": "3.0%жҚўжүӢ", "cls": "ladder-chip-cool muted-text"}, {"text": "жҲҗдәӨйўқ4.48дәҝ", "cls": "ladder-chip-cool muted-text"}, {"text": "еёӮеҖј154дәҝ", "cls": "ladder-chip-cool muted-text"}, {"text": "жўҜйҳҹе®Ңж•ҙ", "cls": "ladder-chip-cool muted-text"}, {"text": "еҫ®еһӢз©ҝи¶Ҡ", "cls": "ladder-chip-cool muted-text"}, {"text": "еӣҪиө„ж”№йқ©", "cls": "ladder-chip-cool muted-text"}]}], "capacityLabel": "еј№жҖ§зҘЁ", "reason": "<span class=\"reason-bits\">еүҚжҺ’йҫҷеӨҙжўҜйҳҹ В· жўҜйҳҹи·ҹйҡҸ В· жһҒејәдё»зәҝ В· зӘҒз ҙж–°й«ҳ(3жқҝ) В· жё©е’Ңж”ҫйҮҸ В· ж—©е°Ғ В· йҮҸд»·е…ұжҢҜ В· й«ҳеәҰеҺӢеҲ¶ В· ж–ӯжқҝйЈҺйҷ©й«ҳ</span><div class=\"exp-wrap\"><div class=\"exp-row\"><span class=\"exp-pill pill-pre\">йў„жңҹ</span>дҪҺејҖпјҲ-2%~+0%%пјү+ з«һд»·йҮҸиғҪвүҘ0.20дәҝ</div><div class=\"exp-row\"><span class=\"exp-pill pill-hi\">и¶…йў„жңҹ</span>й«ҳејҖвүҘ+0%% + з«һд»·йҮҸиғҪвүҘ0.20дәҝ</div><div class=\"exp-row\"><span class=\"exp-pill pill-lo\">дҪҺйў„жңҹ</span>дҪҺдәҺ-2%% жҲ– з«һд»·йҮҸиғҪ<0.14дәҝ</div></div>", "factorRank": 8, "watchRank": 1, "watchGroup": "й«ҳдҪҚеҲҶжӯ§", "scoreLabel": "и§ӮеҜҹеӣ еӯҗ", "scoreSubLabel": "й«ҳдҪҚеҲҶжӯ§ В· еҸӘи§ӮеҜҹ"}, {"name": "еӨӘжһҒе®һдёҡ", "code": "600667", "lbc": 1, "hy": "е·ҘзЁӢе’ЁиҜў", "fundYi": 15.81567, "open": 0, "predTheme": "еӣҪиө„ж”№йқ©", "predThemeCanonical": "еӣҪиө„ж”№йқ©", "hasTier": true, "cjeYi": 47.98990336, "qualityLabel": "", "qualityScore": 88.8, "nextStep": "1иҝӣ2", "stepRate": 15.0, "stepContextScore": 13, "promoEcology": 22, "heightContextScore": 3, "environmentScore": 27, "leaderFactorScore": 51, "relayFactorScore": 58, "capacityFactorScore": 77, "riskControlScore": 29, "breakRisk": 90, "themePersistScore": 77, "leaderPhilosophyScore": 50, "recentHighSignal": {"available": false, "window": 7, "currentDate": "2026-06-30", "currentHigh": 29.7, "prevHigh": 29.43, "sampleSize": 5, "isRecentHigh": false, "breakoutPct": 0.92}, "thsNewhigh": {}, "themeLadderProfile": {"score": 76, "label": "жўҜйҳҹе®Ңж•ҙ", "leaderBoards": 3, "coreCount": 6, "midCarryCount": 4, "followerCount": 9, "frontCount": 6, "gapCount": 0, "isComplete": true, "hasCarry": true, "leaderName": "жҳҠеҚҺз§‘жҠҖ"}, "_isRecentHigh7d": false, "_breakoutDoubleConfirm": false, "leaderRole": "neutral", "score": 48, "factorScore": 48, "factorBreakdown": {"environment": 27, "market": 39, "themeEnv": 100, "marketGate": -16, "sector": 78, "leader": 51, "relay": 58, "capacity": 77, "risk": 29, "opportunity": 81, "edge": 3, "heightBreakout": 0, "tide": 4}, "factorHint": "зҺҜеўғ27(дј‘жҒҜдјҳе…Ҳ) / жқҝеқ—78 / йҫҷеӨҙ51 / жҺҘеҠӣ58 / е®№йҮҸ77 / йЈҺйҷ©29 / жҪ®жұҗ+4 / жўҜйҳҹ76 / еҸӘи§ӮеҜҹ", "scoreBand": "еҸӘи§ӮеҜҹ", "scoreBandTone": "cool", "superLeaderTone": "", "scoreAction": "дёҚдё»еҠЁжҺҘеҠӣ", "marketGate": {"score": 27, "label": "дј‘жҒҜдјҳе…Ҳ", "action": "дёҚдё»еҠЁжҺҘеҠӣ"}, "sectorTrendScore": 79, "sectorRankScore": 92, "plateRank": 0, "plateName": "", "plateNameCanonical": "", "tideStatus": "observe_candidate", "tideAction": "watch", "tidePhase": "neutral", "tideCoreScore": 57.0, "tideEbbScore": 39.0, "tideAdjust": 4.0, "tideRelayAdjust": 1.0, "tideRiskAdjust": -4.0, "tideWatchAdjust": 12.0, "tideRelayGate": 3.0, "tideHint": "еӣҪиө„ж”№йқ©жңүи§ӮеҜҹд»·еҖјпјҢзӯүеҫ…жғ…з»Ә/йҮҸиғҪ/ж¶ҲжҒҜз»§з»ӯе…ұжҢҜгҖӮ", "tideCaution": "", "factorLabels": {"environment": "еҒҸејұ", "sector": "еҒҸејә", "leader": "еҒҸејұ", "relay": "еҒҸејұ", "capacity": "еҒҸејә", "risk": "еҒҸејұ"}, "tags": [{"text": "1иҝӣ2", "cls": "ladder-chip-cool muted-text"}, {"text": "жһҒејәдё»зәҝ", "cls": "ladder-chip-strong red-text"}, {"text": "и·ҹйЈҺжҳҠеҚҺз§‘жҠҖ", "cls": "ladder-chip-warn orange-text"}, {"text": "жҷӢзә§з”ҹжҖҒејұ", "cls": "ladder-chip-warn orange-text"}, {"text": "й«ҳеәҰеҺӢеҲ¶", "cls": "ladder-chip-warn orange-text"}, {"text": "ж–ӯжқҝйЈҺйҷ©й«ҳ", "cls": "ladder-chip-warn orange-text"}, {"text": "жё©е’Ңж”ҫйҮҸ", "cls": "ladder-chip-cool muted-text"}, {"text": "жңӘејҖ", "cls": "ladder-chip-cool muted-text"}, {"text": "йҰ–е°Ғ09:45", "cls": "ladder-chip-cool muted-text"}, {"text": "йҮҸд»·е…ұжҢҜ", "cls": "ladder-chip-cool muted-text"}, {"text": "йўҳжқҗеҸ‘ж•Ј", "cls": "ladder-chip-cool muted-text"}, {"text": "е°ҒеҚ•15.82дәҝ", "cls": "ladder-chip-cool muted-text"}, {"text": "7.4%жҚўжүӢ", "cls": "ladder-chip-cool muted-text"}, {"text": "жҲҗдәӨйўқ47.99дәҝ", "cls": "ladder-chip-cool muted-text"}, {"text": "еёӮеҖј671дәҝ", "cls": "ladder-chip-cool muted-text"}, {"text": "жўҜйҳҹе®Ңж•ҙ", "cls": "ladder-chip-cool muted-text"}, {"text": "еҫ®еһӢз©ҝи¶Ҡ", "cls": "ladder-chip-cool muted-text"}, {"text": "йҰ–жқҝ", "cls": "ladder-chip-cool muted-text"}, {"text": "еӣҪиө„ж”№йқ©", "cls": "ladder-chip-cool muted-text"}, {"text": "еҚҠеҜјдҪ“", "cls": "ladder-chip-cool muted-text"}, {"text": "е®№йҮҸж ё", "cls": "ladder-chip-warn orange-text"}], "tagRows": [{"tone": "red", "tags": [{"text": "жһҒејәдё»зәҝ", "cls": "ladder-chip-strong red-text"}]}, {"tone": "orange", "tags": [{"text": "и·ҹйЈҺжҳҠеҚҺз§‘жҠҖ", "cls": "ladder-chip-warn orange-text"}, {"text": "жҷӢзә§з”ҹжҖҒејұ", "cls": "ladder-chip-warn orange-text"}, {"text": "й«ҳеәҰеҺӢеҲ¶", "cls": "ladder-chip-warn orange-text"}, {"text": "ж–ӯжқҝйЈҺйҷ©й«ҳ", "cls": "ladder-chip-warn orange-text"}, {"text": "е®№йҮҸж ё", "cls": "ladder-chip-warn orange-text"}]}, {"tone": "muted", "tags": [{"text": "1иҝӣ2", "cls": "ladder-chip-cool muted-text"}, {"text": "жё©е’Ңж”ҫйҮҸ", "cls": "ladder-chip-cool muted-text"}, {"text": "жңӘејҖ", "cls": "ladder-chip-cool muted-text"}, {"text": "йҰ–е°Ғ09:45", "cls": "ladder-chip-cool muted-text"}, {"text": "йҮҸд»·е…ұжҢҜ", "cls": "ladder-chip-cool muted-text"}, {"text": "йўҳжқҗеҸ‘ж•Ј", "cls": "ladder-chip-cool muted-text"}, {"text": "е°ҒеҚ•15.82дәҝ", "cls": "ladder-chip-cool muted-text"}, {"text": "7.4%жҚўжүӢ", "cls": "ladder-chip-cool muted-text"}, {"text": "жҲҗдәӨйўқ47.99дәҝ", "cls": "ladder-chip-cool muted-text"}, {"text": "еёӮеҖј671дәҝ", "cls": "ladder-chip-cool muted-text"}, {"text": "жўҜйҳҹе®Ңж•ҙ", "cls": "ladder-chip-cool muted-text"}, {"text": "еҫ®еһӢз©ҝи¶Ҡ", "cls": "ladder-chip-cool muted-text"}, {"text": "йҰ–жқҝ", "cls": "ladder-chip-cool muted-text"}, {"text": "еӣҪиө„ж”№йқ©", "cls": "ladder-chip-cool muted-text"}, {"text": "еҚҠеҜјдҪ“", "cls": "ladder-chip-cool muted-text"}]}], "capacityLabel": "е®№йҮҸж ё", "reason": "<span class=\"reason-bits\">жўҜйҳҹи·ҹйҡҸ В· жһҒејәдё»зәҝ В· йўҳжқҗжҢҒз»ӯ В· йўҳжқҗиҒ”еҠЁ В· жё©е’Ңж”ҫйҮҸ В· е°ҒеҚ•еҒҸејә В· е°ҒжқҝзЁі В· й«ҳеәҰеҺӢеҲ¶ В· ж–ӯжқҝйЈҺйҷ©й«ҳ</span><div class=\"exp-wrap\"><div class=\"exp-row\"><span class=\"exp-pill pill-pre\">йў„жңҹ</span>дҪҺејҖпјҲ-2%~+0%%пјү+ з«һд»·йҮҸиғҪвүҘ2.16дәҝ</div><div class=\"exp-row\"><span class=\"exp-pill pill-hi\">и¶…йў„жңҹ</span>й«ҳејҖвүҘ+0%% + з«һд»·йҮҸиғҪвүҘ2.16дәҝ</div><div class=\"exp-row\"><span class=\"exp-pill pill-lo\">дҪҺйў„жңҹ</span>дҪҺдәҺ-2%% жҲ– з«һд»·йҮҸиғҪ<1.51дәҝ</div></div>", "factorRank": 7, "watchRank": 2, "watchGroup": "е®№йҮҸж ёеҝғ", "scoreLabel": "и§ӮеҜҹеӣ еӯҗ", "scoreSubLabel": "е®№йҮҸж ёеҝғ В· еҸӘи§ӮеҜҹ"}, {"name": "еҚҺе®үиҜҒеҲё", "code": "600909", "lbc": 1, "hy": "иҜҒеҲёв…Ў", "fundYi": 11.46691818, "open": 0, "predTheme": "еӣҪиө„ж”№йқ©", "predThemeCanonical": "еӣҪиө„ж”№йқ©", "hasTier": true, "cjeYi": 23.0718512, "qualityLabel": "", "qualityScore": 68.22064774016664, "nextStep": "1иҝӣ2", "stepRate": 15.0, "stepContextScore": 13, "promoEcology": 22, "heightContextScore": 3, "environmentScore": 27, "leaderFactorScore": 48, "relayFactorScore": 51, "capacityFactorScore": 74, "riskControlScore": 29, "breakRisk": 90, "themePersistScore": 77, "leaderPhilosophyScore": 49, "recentHighSignal": {"available": false, "window": 7, "currentDate": "2026-06-30", "currentHigh": 11.7, "prevHigh": 12.91, "sampleSize": 5, "isRecentHigh": false, "breakoutPct": -9.37}, "thsNewhigh": {}, "themeLadderProfile": {"score": 76, "label": "жўҜйҳҹе®Ңж•ҙ", "leaderBoards": 3, "coreCount": 6, "midCarryCount": 4, "followerCount": 9, "frontCount": 6, "gapCount": 0, "isComplete": true, "hasCarry": true, "leaderName": "жҳҠеҚҺз§‘жҠҖ"}, "_isRecentHigh7d": false, "_breakoutDoubleConfirm": false, "leaderRole": "neutral", "score": 45, "factorScore": 45, "factorBreakdown": {"environment": 27, "market": 39, "themeEnv": 100, "marketGate": -16, "sector": 76, "leader": 48, "relay": 51, "capacity": 74, "risk": 29, "opportunity": 81, "edge": 3, "heightBreakout": 0, "tide": 4}, "factorHint": "зҺҜеўғ27(дј‘жҒҜдјҳе…Ҳ) / жқҝеқ—76 / йҫҷеӨҙ48 / жҺҘеҠӣ51 / е®№йҮҸ74 / йЈҺйҷ©29 / жҪ®жұҗ+4 / жўҜйҳҹ76 / еҸӘи§ӮеҜҹ", "scoreBand": "еҸӘи§ӮеҜҹ", "scoreBandTone": "cool", "superLeaderTone": "", "scoreAction": "дёҚдё»еҠЁжҺҘеҠӣ", "marketGate": {"score": 27, "label": "дј‘жҒҜдјҳе…Ҳ", "action": "дёҚдё»еҠЁжҺҘеҠӣ"}, "sectorTrendScore": 79, "sectorRankScore": 92, "plateRank": 0, "plateName": "", "plateNameCanonical": "", "tideStatus": "observe_candidate", "tideAction": "watch", "tidePhase": "neutral", "tideCoreScore": 57.0, "tideEbbScore": 39.0, "tideAdjust": 4.0, "tideRelayAdjust": 1.0, "tideRiskAdjust": -4.0, "tideWatchAdjust": 12.0, "tideRelayGate": 3.0, "tideHint": "еӣҪиө„ж”№йқ©жңүи§ӮеҜҹд»·еҖјпјҢзӯүеҫ…жғ…з»Ә/йҮҸиғҪ/ж¶ҲжҒҜз»§з»ӯе…ұжҢҜгҖӮ", "tideCaution": "", "factorLabels": {"environment": "еҒҸејұ", "sector": "еҒҸејә", "leader": "еҒҸејұ", "relay": "еҒҸејұ", "capacity": "еҒҸејә", "risk": "еҒҸејұ"}, "tags": [{"text": "1иҝӣ2", "cls": "ladder-chip-cool muted-text"}, {"text": "жһҒејәдё»зәҝ", "cls": "ladder-chip-strong red-text"}, {"text": "и·ҹйЈҺжҳҠеҚҺз§‘жҠҖ", "cls": "ladder-chip-warn orange-text"}, {"text": "жҷӢзә§з”ҹжҖҒејұ", "cls": "ladder-chip-warn orange-text"}, {"text": "й«ҳеәҰеҺӢеҲ¶", "cls": "ladder-chip-warn orange-text"}, {"text": "ж–ӯжқҝйЈҺйҷ©й«ҳ", "cls": "ladder-chip-warn orange-text"}, {"text": "жё©е’Ңж”ҫйҮҸ", "cls": "ladder-chip-cool muted-text"}, {"text": "жңӘејҖ", "cls": "ladder-chip-cool muted-text"}, {"text": "йҰ–е°Ғ10:07", "cls": "ladder-chip-cool muted-text"}, {"text": "йҮҸд»·е…ұжҢҜ", "cls": "ladder-chip-cool muted-text"}, {"text": "е°ҒеҚ•11.47дәҝ", "cls": "ladder-chip-cool muted-text"}, {"text": "3.9%жҚўжүӢ", "cls": "ladder-chip-cool muted-text"}, {"text": "жҲҗдәӨйўқ23.07дәҝ", "cls": "ladder-chip-cool muted-text"}, {"text": "еёӮеҖј614дәҝ", "cls": "ladder-chip-cool muted-text"}, {"text": "жўҜйҳҹе®Ңж•ҙ", "cls": "ladder-chip-cool muted-text"}, {"text": "еҫ®еһӢз©ҝи¶Ҡ", "cls": "ladder-chip-cool muted-text"}, {"text": "йҰ–жқҝ", "cls": "ladder-chip-cool muted-text"}, {"text": "еӣҪиө„ж”№йқ©", "cls": "ladder-chip-cool muted-text"}, {"text": "е®№йҮҸж ё", "cls": "ladder-chip-warn orange-text"}], "tagRows": [{"tone": "red", "tags": [{"text": "жһҒејәдё»зәҝ", "cls": "ladder-chip-strong red-text"}]}, {"tone": "orange", "tags": [{"text": "и·ҹйЈҺжҳҠеҚҺз§‘жҠҖ", "cls": "ladder-chip-warn orange-text"}, {"text": "жҷӢзә§з”ҹжҖҒејұ", "cls": "ladder-chip-warn orange-text"}, {"text": "й«ҳеәҰеҺӢеҲ¶", "cls": "ladder-chip-warn orange-text"}, {"text": "ж–ӯжқҝйЈҺйҷ©й«ҳ", "cls": "ladder-chip-warn orange-text"}, {"text": "е®№йҮҸж ё", "cls": "ladder-chip-warn orange-text"}]}, {"tone": "muted", "tags": [{"text": "1иҝӣ2", "cls": "ladder-chip-cool muted-text"}, {"text": "жё©е’Ңж”ҫйҮҸ", "cls": "ladder-chip-cool muted-text"}, {"text": "жңӘејҖ", "cls": "ladder-chip-cool muted-text"}, {"text": "йҰ–е°Ғ10:07", "cls": "ladder-chip-cool muted-text"}, {"text": "йҮҸд»·е…ұжҢҜ", "cls": "ladder-chip-cool muted-text"}, {"text": "е°ҒеҚ•11.47дәҝ", "cls": "ladder-chip-cool muted-text"}, {"text": "3.9%жҚўжүӢ", "cls": "ladder-chip-cool muted-text"}, {"text": "жҲҗдәӨйўқ23.07дәҝ", "cls": "ladder-chip-cool muted-text"}, {"text": "еёӮеҖј614дәҝ", "cls": "ladder-chip-cool muted-text"}, {"text": "жўҜйҳҹе®Ңж•ҙ", "cls": "ladder-chip-cool muted-text"}, {"text": "еҫ®еһӢз©ҝи¶Ҡ", "cls": "ladder-chip-cool muted-text"}, {"text": "йҰ–жқҝ", "cls": "ladder-chip-cool muted-text"}, {"text": "еӣҪиө„ж”№йқ©", "cls": "ladder-chip-cool muted-text"}]}], "capacityLabel": "е®№йҮҸж ё", "reason": "<span class=\"reason-bits\">жўҜйҳҹи·ҹйҡҸ В· жһҒејәдё»зәҝ В· йўҳжқҗжҢҒз»ӯ В· йўҳжқҗиҒ”еҠЁ В· жё©е’Ңж”ҫйҮҸ В· е°ҒеҚ•еҒҸејә В· е°ҒжқҝзЁі В· й«ҳеәҰеҺӢеҲ¶ В· ж–ӯжқҝйЈҺйҷ©й«ҳ</span><div class=\"exp-wrap\"><div class=\"exp-row\"><span class=\"exp-pill pill-pre\">йў„жңҹ</span>дҪҺејҖпјҲ-2%~+0%%пјү+ з«һд»·йҮҸиғҪвүҘ1.04дәҝ</div><div class=\"exp-row\"><span class=\"exp-pill pill-hi\">и¶…йў„жңҹ</span>й«ҳејҖвүҘ+0%% + з«һд»·йҮҸиғҪвүҘ1.04дәҝ</div><div class=\"exp-row\"><span class=\"exp-pill pill-lo\">дҪҺйў„жңҹ</span>дҪҺдәҺ-2%% жҲ– з«һд»·йҮҸиғҪ<0.73дәҝ</div></div>", "factorRank": 12, "watchRank": 3, "watchGroup": "е®№йҮҸж ёеҝғ", "scoreLabel": "и§ӮеҜҹеӣ еӯҗ", "scoreSubLabel": "е®№йҮҸж ёеҝғ В· еҸӘи§ӮеҜҹ"}, {"name": "е…ҲеҜјеҹәз”ө", "code": "600641", "lbc": 2, "hy": "еҚҠеҜјдҪ“", "fundYi": 3.72193932, "open": 1, "predTheme": "еҚҠеҜјдҪ“", "predThemeCanonical": "еҚҠеҜјдҪ“", "hasTier": true, "cjeYi": 22.75116624, "qualityLabel": "жё©е’Ңж”ҫйҮҸ", "qualityScore": 84.0, "nextStep": "2иҝӣ3", "stepRate": 15.8, "stepContextScore": 44, "promoEcology": 22, "heightContextScore": 3, "environmentScore": 27, "leaderFactorScore": 61, "relayFactorScore": 60, "capacityFactorScore": 77, "riskControlScore": 29, "breakRisk": 90, "themePersistScore": 66, "leaderPhilosophyScore": 46, "recentHighSignal": {"available": false, "window": 7, "currentDate": "2026-06-30", "currentHigh": 39.86, "prevHigh": 39.36, "sampleSize": 5, "isRecentHigh": false, "breakoutPct": 1.27}, "thsNewhigh": {}, "themeLadderProfile": {"score": 78, "label": "жўҜйҳҹе®Ңж•ҙ", "leaderBoards": 3, "coreCount": 6, "midCarryCount": 4, "followerCount": 8, "frontCount": 6, "gapCount": 0, "isComplete": true, "hasCarry": true, "leaderName": "еӨҡж°ҹеӨҡ"}, "_isRecentHigh7d": false, "_breakoutDoubleConfirm": false, "leaderRole": "core", "score": 49, "factorScore": 49, "factorBreakdown": {"environment": 27, "market": 39, "themeEnv": 100, "marketGate": -16, "sector": 65, "leader": 61, "relay": 60, "capacity": 77, "risk": 29, "opportunity": 81, "edge": 4, "heightBreakout": 0, "tide": 4}, "factorHint": "зҺҜеўғ27(дј‘жҒҜдјҳе…Ҳ) / жқҝеқ—65 / йҫҷеӨҙ61 / жҺҘеҠӣ60 / е®№йҮҸ77 / йЈҺйҷ©29 / жҪ®жұҗ+4 / жўҜйҳҹ78 / еҸӘи§ӮеҜҹ", "scoreBand": "еҸӘи§ӮеҜҹ", "scoreBandTone": "cool", "superLeaderTone": "", "scoreAction": "дёҚдё»еҠЁжҺҘеҠӣ", "marketGate": {"score": 27, "label": "дј‘жҒҜдјҳе…Ҳ", "action": "дёҚдё»еҠЁжҺҘеҠӣ"}, "sectorTrendScore": 69, "sectorRankScore": 74, "plateRank": 0, "plateName": "", "plateNameCanonical": "", "tideStatus": "observe_candidate", "tideAction": "watch", "tidePhase": "neutral", "tideCoreScore": 57.0, "tideEbbScore": 39.0, "tideAdjust": 4.0, "tideRelayAdjust": 1.0, "tideRiskAdjust": -4.0, "tideWatchAdjust": 12.0, "tideRelayGate": 3.0, "tideHint": "еҚҠеҜјдҪ“жңүи§ӮеҜҹд»·еҖјпјҢзӯүеҫ…жғ…з»Ә/йҮҸиғҪ/ж¶ҲжҒҜз»§з»ӯе…ұжҢҜгҖӮ", "tideCaution": "", "factorLabels": {"environment": "еҒҸејұ", "sector": "дёӯжҖ§", "leader": "дёӯжҖ§", "relay": "дёӯжҖ§", "capacity": "еҒҸејә", "risk": "еҒҸејұ"}, "tags": [{"text": "2иҝӣ3", "cls": "ladder-chip-strong red-text"}, {"text": "2жқҝ", "cls": "ladder-chip-cool muted-text"}, {"text": "ејәдё»зәҝ", "cls": "ladder-chip-strong red-text"}, {"text": "ж ёеҝғжўҜйҳҹ", "cls": "ladder-chip-strong red-text"}, {"text": "и·ҹйЈҺеӨҡж°ҹеӨҡ", "cls": "ladder-chip-warn orange-text"}, {"text": "жҷӢзә§з”ҹжҖҒејұ", "cls": "ladder-chip-warn orange-text"}, {"text": "й«ҳеәҰеҺӢеҲ¶", "cls": "ladder-chip-warn orange-text"}, {"text": "ж–ӯжқҝйЈҺйҷ©й«ҳ", "cls": "ladder-chip-warn orange-text"}, {"text": "1ж¬ЎејҖжқҝ", "cls": "ladder-chip-warn orange-text"}, {"text": "жё©е’Ңж”ҫйҮҸ", "cls": "ladder-chip-cool muted-text"}, {"text": "йҰ–е°Ғ10:00", "cls": "ladder-chip-cool muted-text"}, {"text": "йҮҸд»·е…ұжҢҜ", "cls": "ladder-chip-cool muted-text"}, {"text": "йўҳжқҗеҸ‘ж•Ј", "cls": "ladder-chip-cool muted-text"}, {"text": "е°ҒеҚ•3.72дәҝ", "cls": "ladder-chip-cool muted-text"}, {"text": "5.7%жҚўжүӢ", "cls": "ladder-chip-cool muted-text"}, {"text": "жҲҗдәӨйўқ22.75дәҝ", "cls": "ladder-chip-cool muted-text"}, {"text": "еёӮеҖј415дәҝ", "cls": "ladder-chip-cool muted-text"}, {"text": "жўҜйҳҹе®Ңж•ҙ", "cls": "ladder-chip-cool muted-text"}, {"text": "еҫ®еһӢз©ҝи¶Ҡ", "cls": "ladder-chip-cool muted-text"}, {"text": "еҚҠеҜјдҪ“", "cls": "ladder-chip-cool muted-text"}, {"text": "еҲӣжҠ•", "cls": "ladder-chip-cool muted-text"}, {"text": "е®№йҮҸж ё", "cls": "ladder-chip-warn orange-text"}], "tagRows": [{"tone": "red", "tags": [{"text": "2иҝӣ3", "cls": "ladder-chip-strong red-text"}, {"text": "ејәдё»зәҝ", "cls": "ladder-chip-strong red-text"}, {"text": "ж ёеҝғжўҜйҳҹ", "cls": "ladder-chip-strong red-text"}]}, {"tone": "orange", "tags": [{"text": "и·ҹйЈҺеӨҡж°ҹеӨҡ", "cls": "ladder-chip-warn orange-text"}, {"text": "жҷӢзә§з”ҹжҖҒејұ", "cls": "ladder-chip-warn orange-text"}, {"text": "й«ҳеәҰеҺӢеҲ¶", "cls": "ladder-chip-warn orange-text"}, {"text": "ж–ӯжқҝйЈҺйҷ©й«ҳ", "cls": "ladder-chip-warn orange-text"}, {"text": "1ж¬ЎејҖжқҝ", "cls": "ladder-chip-warn orange-text"}, {"text": "е®№йҮҸж ё", "cls": "ladder-chip-warn orange-text"}]}, {"tone": "muted", "tags": [{"text": "2жқҝ", "cls": "ladder-chip-cool muted-text"}, {"text": "жё©е’Ңж”ҫйҮҸ", "cls": "ladder-chip-cool muted-text"}, {"text": "йҰ–е°Ғ10:00", "cls": "ladder-chip-cool muted-text"}, {"text": "йҮҸд»·е…ұжҢҜ", "cls": "ladder-chip-cool muted-text"}, {"text": "йўҳжқҗеҸ‘ж•Ј", "cls": "ladder-chip-cool muted-text"}, {"text": "е°ҒеҚ•3.72дәҝ", "cls": "ladder-chip-cool muted-text"}, {"text": "5.7%жҚўжүӢ", "cls": "ladder-chip-cool muted-text"}, {"text": "жҲҗдәӨйўқ22.75дәҝ", "cls": "ladder-chip-cool muted-text"}, {"text": "еёӮеҖј415дәҝ", "cls": "ladder-chip-cool muted-text"}, {"text": "жўҜйҳҹе®Ңж•ҙ", "cls": "ladder-chip-cool muted-text"}, {"text": "еҫ®еһӢз©ҝи¶Ҡ", "cls": "ladder-chip-cool muted-text"}, {"text": "еҚҠеҜјдҪ“", "cls": "ladder-chip-cool muted-text"}, {"text": "еҲӣжҠ•", "cls": "ladder-chip-cool muted-text"}]}], "capacityLabel": "е®№йҮҸж ё", "reason": "<span class=\"reason-bits\">ж ёеҝғжўҜйҳҹ В· жўҜйҳҹи·ҹйҡҸ В· ејәдё»зәҝ В· йўҳжқҗжҢҒз»ӯ В· жё©е’Ңж”ҫйҮҸ В· е°ҒжқҝзЁі В· е®№йҮҸеӨҹ В· й«ҳеәҰеҺӢеҲ¶ В· ж–ӯжқҝйЈҺйҷ©й«ҳ</span><div class=\"exp-wrap\"><div class=\"exp-row\"><span class=\"exp-pill pill-pre\">йў„жңҹ</span>дҪҺејҖпјҲ-2%~+0%%пјү+ з«һд»·йҮҸиғҪвүҘ1.02дәҝ</div><div class=\"exp-row\"><span class=\"exp-pill pill-hi\">и¶…йў„жңҹ</span>й«ҳејҖвүҘ+0%% + з«һд»·йҮҸиғҪвүҘ1.02дәҝ</div><div class=\"exp-row\"><span class=\"exp-pill pill-lo\">дҪҺйў„жңҹ</span>дҪҺдәҺ-2%% жҲ– з«һд»·йҮҸиғҪ<0.72дәҝ</div></div>", "factorRank": 6, "watchRank": 4, "watchGroup": "е®№йҮҸж ёеҝғ", "scoreLabel": "и§ӮеҜҹеӣ еӯҗ", "scoreSubLabel": "е®№йҮҸж ёеҝғ В· еҸӘи§ӮеҜҹ"}, {"name": "и¶…еЈ°з”өеӯҗ", "code": "000823", "lbc": 1, "hy": "е…ғд»¶", "fundYi": 2.81573741, "open": 0, "predTheme": "еӣҪиө„ж”№йқ©", "predThemeCanonical": "еӣҪиө„ж”№йқ©", "hasTier": true, "cjeYi": 17.09457024, "qualityLabel": "", "qualityScore": 61.869921775462956, "nextStep": "1иҝӣ2", "stepRate": 15.0, "stepContextScore": 13, "promoEcology": 22, "heightContextScore": 3, "environmentScore": 27, "leaderFactorScore": 47, "relayFactorScore": 45, "capacityFactorScore": 91, "riskControlScore": 29, "breakRisk": 90, "themePersistScore": 77, "leaderPhilosophyScore": 50, "recentHighSignal": {"available": false, "window": 7, "currentDate": "2026-06-30", "currentHigh": 26.23, "prevHigh": 29.77, "sampleSize": 5, "isRecentHigh": false, "breakoutPct": -11.89}, "thsNewhigh": {}, "themeLadderProfile": {"score": 76, "label": "жўҜйҳҹе®Ңж•ҙ", "leaderBoards": 3, "coreCount": 6, "midCarryCount": 4, "followerCount": 9, "frontCount": 6, "gapCount": 0, "isComplete": true, "hasCarry": true, "leaderName": "жҳҠеҚҺз§‘жҠҖ"}, "_isRecentHigh7d": false, "_breakoutDoubleConfirm": false, "leaderRole": "neutral", "score": 47, "factorScore": 47, "factorBreakdown": {"environment": 27, "market": 39, "themeEnv": 100, "marketGate": -16, "sector": 78, "leader": 47, "relay": 45, "capacity": 91, "risk": 29, "opportunity": 81, "edge": 4, "heightBreakout": 0, "tide": 4}, "factorHint": "зҺҜеўғ27(дј‘жҒҜдјҳе…Ҳ) / жқҝеқ—78 / йҫҷеӨҙ47 / жҺҘеҠӣ45 / е®№йҮҸ91 / йЈҺйҷ©29 / жҪ®жұҗ+4 / жўҜйҳҹ76 / еҸӘи§ӮеҜҹ", "scoreBand": "еҸӘи§ӮеҜҹ", "scoreBandTone": "cool", "superLeaderTone": "", "scoreAction": "дёҚдё»еҠЁжҺҘеҠӣ", "marketGate": {"score": 27, "label": "дј‘жҒҜдјҳе…Ҳ", "action": "дёҚдё»еҠЁжҺҘеҠӣ"}, "sectorTrendScore": 79, "sectorRankScore": 92, "plateRank": 0, "plateName": "", "plateNameCanonical": "", "tideStatus": "observe_candidate", "tideAction": "watch", "tidePhase": "neutral", "tideCoreScore": 57.0, "tideEbbScore": 39.0, "tideAdjust": 4.0, "tideRelayAdjust": 1.0, "tideRiskAdjust": -4.0, "tideWatchAdjust": 12.0, "tideRelayGate": 3.0, "tideHint": "еӣҪиө„ж”№йқ©жңүи§ӮеҜҹд»·еҖјпјҢзӯүеҫ…жғ…з»Ә/йҮҸиғҪ/ж¶ҲжҒҜз»§з»ӯе…ұжҢҜгҖӮ", "tideCaution": "", "factorLabels": {"environment": "еҒҸејұ", "sector": "еҒҸејә", "leader": "еҒҸејұ", "relay": "еҒҸејұ", "capacity": "ејә", "risk": "еҒҸејұ"}, "tags": [{"text": "1иҝӣ2", "cls": "ladder-chip-cool muted-text"}, {"text": "жһҒејәдё»зәҝ", "cls": "ladder-chip-strong red-text"}, {"text": "и·ҹйЈҺжҳҠеҚҺз§‘жҠҖ", "cls": "ladder-chip-warn orange-text"}, {"text": "жҷӢзә§з”ҹжҖҒејұ", "cls": "ladder-chip-warn orange-text"}, {"text": "й«ҳеәҰеҺӢеҲ¶", "cls": "ladder-chip-warn orange-text"}, {"text": "ж–ӯжқҝйЈҺйҷ©й«ҳ", "cls": "ladder-chip-warn orange-text"}, {"text": "жё©е’Ңж”ҫйҮҸ", "cls": "ladder-chip-cool muted-text"}, {"text": "жңӘејҖ", "cls": "ladder-chip-cool muted-text"}, {"text": "йҰ–е°Ғ09:49", "cls": "ladder-chip-cool muted-text"}, {"text": "йҮҸд»·е…ұжҢҜ", "cls": "ladder-chip-cool muted-text"}, {"text": "йўҳжқҗеҸ‘ж•Ј", "cls": "ladder-chip-cool muted-text"}, {"text": "е°ҒеҚ•2.82дәҝ", "cls": "ladder-chip-cool muted-text"}, {"text": "10.5%жҚўжүӢ", "cls": "ladder-chip-cool muted-text"}, {"text": "жҲҗдәӨйўқ17.09дәҝ", "cls": "ladder-chip-cool muted-text"}, {"text": "еёӮеҖј168дәҝ", "cls": "ladder-chip-cool muted-text"}, {"text": "жўҜйҳҹе®Ңж•ҙ", "cls": "ladder-chip-cool muted-text"}, {"text": "еҫ®еһӢз©ҝи¶Ҡ", "cls": "ladder-chip-cool muted-text"}, {"text": "йҰ–жқҝ", "cls": "ladder-chip-cool muted-text"}, {"text": "еӣҪиө„ж”№йқ©", "cls": "ladder-chip-cool muted-text"}, {"text": "жҜ”дәҡиҝӘжҰӮеҝө", "cls": "ladder-chip-cool muted-text"}, {"text": "е®№йҮҸж ё", "cls": "ladder-chip-warn orange-text"}], "tagRows": [{"tone": "red", "tags": [{"text": "жһҒејәдё»зәҝ", "cls": "ladder-chip-strong red-text"}]}, {"tone": "orange", "tags": [{"text": "и·ҹйЈҺжҳҠеҚҺз§‘жҠҖ", "cls": "ladder-chip-warn orange-text"}, {"text": "жҷӢзә§з”ҹжҖҒејұ", "cls": "ladder-chip-warn orange-text"}, {"text": "й«ҳеәҰеҺӢеҲ¶", "cls": "ladder-chip-warn orange-text"}, {"text": "ж–ӯжқҝйЈҺйҷ©й«ҳ", "cls": "ladder-chip-warn orange-text"}, {"text": "е®№йҮҸж ё", "cls": "ladder-chip-warn orange-text"}]}, {"tone": "muted", "tags": [{"text": "1иҝӣ2", "cls": "ladder-chip-cool muted-text"}, {"text": "жё©е’Ңж”ҫйҮҸ", "cls": "ladder-chip-cool muted-text"}, {"text": "жңӘејҖ", "cls": "ladder-chip-cool muted-text"}, {"text": "йҰ–е°Ғ09:49", "cls": "ladder-chip-cool muted-text"}, {"text": "йҮҸд»·е…ұжҢҜ", "cls": "ladder-chip-cool muted-text"}, {"text": "йўҳжқҗеҸ‘ж•Ј", "cls": "ladder-chip-cool muted-text"}, {"text": "е°ҒеҚ•2.82дәҝ", "cls": "ladder-chip-cool muted-text"}, {"text": "10.5%жҚўжүӢ", "cls": "ladder-chip-cool muted-text"}, {"text": "жҲҗдәӨйўқ17.09дәҝ", "cls": "ladder-chip-cool muted-text"}, {"text": "еёӮеҖј168дәҝ", "cls": "ladder-chip-cool muted-text"}, {"text": "жўҜйҳҹе®Ңж•ҙ", "cls": "ladder-chip-cool muted-text"}, {"text": "еҫ®еһӢз©ҝи¶Ҡ", "cls": "ladder-chip-cool muted-text"}, {"text": "йҰ–жқҝ", "cls": "ladder-chip-cool muted-text"}, {"text": "еӣҪиө„ж”№йқ©", "cls": "ladder-chip-cool muted-text"}, {"text": "жҜ”дәҡиҝӘжҰӮеҝө", "cls": "ladder-chip-cool muted-text"}]}], "capacityLabel": "е®№йҮҸж ё", "reason": "<span class=\"reason-bits\">жўҜйҳҹи·ҹйҡҸ В· жһҒејәдё»зәҝ В· йўҳжқҗжҢҒз»ӯ В· йўҳжқҗиҒ”еҠЁ В· жё©е’Ңж”ҫйҮҸ В· е°ҒжқҝзЁі В· е®№йҮҸеӨҹ В· й«ҳеәҰеҺӢеҲ¶ В· ж–ӯжқҝйЈҺйҷ©й«ҳ</span><div class=\"exp-wrap\"><div class=\"exp-row\"><span class=\"exp-pill pill-pre\">йў„жңҹ</span>дҪҺејҖпјҲ-2%~+0%%пјү+ з«һд»·йҮҸиғҪвүҘ0.77дәҝ</div><div class=\"exp-row\"><span class=\"exp-pill pill-hi\">и¶…йў„жңҹ</span>й«ҳејҖвүҘ+0%% + з«һд»·йҮҸиғҪвүҘ0.77дәҝ</div><div class=\"exp-row\"><span class=\"exp-pill pill-lo\">дҪҺйў„жңҹ</span>дҪҺдәҺ-2%% жҲ– з«һд»·йҮҸиғҪ<0.54дәҝ</div></div>", "factorRank": 10, "watchRank": 5, "watchGroup": "е®№йҮҸж ёеҝғ", "scoreLabel": "и§ӮеҜҹеӣ еӯҗ", "scoreSubLabel": "е®№йҮҸж ёеҝғ В· еҸӘи§ӮеҜҹ"}, {"name": "зҒ«зӮ¬з”өеӯҗ", "code": "603678", "lbc": 1, "hy": "еҶӣе·Ҙз”өеӯҗ", "fundYi": 3.56219184, "open": 0, "predTheme": "ж–°жқҗж–ҷ", "predThemeCanonical": "ж–°жқҗж–ҷ", "hasTier": true, "cjeYi": 20.71485136, "qualityLabel": "", "qualityScore": 64.40762283969227, "nextStep": "1иҝӣ2", "stepRate": 15.0, "stepContextScore": 13, "promoEcology": 22, "heightContextScore": 3, "environmentScore": 27, "leaderFactorScore": 45, "relayFactorScore": 46, "capacityFactorScore": 75, "riskControlScore": 33, "breakRisk": 90, "themePersistScore": 73, "leaderPhilosophyScore": 48, "recentHighSignal": {"available": false, "window": 7, "currentDate": "2026-06-30", "currentHigh": 84.88, "prevHigh": 87.3, "sampleSize": 5, "isRecentHigh": false, "breakoutPct": -2.77}, "thsNewhigh": {}, "themeLadderProfile": {"score": 77, "label": "жўҜйҳҹе®Ңж•ҙ", "leaderBoards": 3, "coreCount": 4, "midCarryCount": 3, "followerCount": 7, "frontCount": 4, "gapCount": 0, "isComplete": true, "hasCarry": true, "leaderName": "еӨҡж°ҹеӨҡ"}, "_isRecentHigh7d": false, "_breakoutDoubleConfirm": false, "leaderRole": "neutral", "score": 43, "factorScore": 43, "factorBreakdown": {"environment": 27, "market": 39, "themeEnv": 100, "marketGate": -16, "sector": 72, "leader": 45, "relay": 46, "capacity": 75, "risk": 33, "opportunity": 81, "edge": 3, "heightBreakout": 0, "tide": 4}, "factorHint": "зҺҜеўғ27(дј‘жҒҜдјҳе…Ҳ) / жқҝеқ—72 / йҫҷеӨҙ45 / жҺҘеҠӣ46 / е®№йҮҸ75 / йЈҺйҷ©33 / жҪ®жұҗ+4 / жўҜйҳҹ77 / еҸӘи§ӮеҜҹ", "scoreBand": "еҸӘи§ӮеҜҹ", "scoreBandTone": "cool", "superLeaderTone": "", "scoreAction": "дёҚдё»еҠЁжҺҘеҠӣ", "marketGate": {"score": 27, "label": "дј‘жҒҜдјҳе…Ҳ", "action": "дёҚдё»еҠЁжҺҘеҠӣ"}, "sectorTrendScore": 75, "sectorRankScore": 88, "plateRank": 0, "plateName": "", "plateNameCanonical": "", "tideStatus": "observe_candidate", "tideAction": "watch", "tidePhase": "neutral", "tideCoreScore": 58.0, "tideEbbScore": 39.0, "tideAdjust": 4.0, "tideRelayAdjust": 1.0, "tideRiskAdjust": -4.0, "tideWatchAdjust": 12.0, "tideRelayGate": 3.0, "tideHint": "ж–°жқҗж–ҷжңүи§ӮеҜҹд»·еҖјпјҢзӯүеҫ…жғ…з»Ә/йҮҸиғҪ/ж¶ҲжҒҜз»§з»ӯе…ұжҢҜгҖӮ", "tideCaution": "", "factorLabels": {"environment": "еҒҸејұ", "sector": "еҒҸејә", "leader": "еҒҸејұ", "relay": "еҒҸејұ", "capacity": "еҒҸејә", "risk": "еҒҸејұ"}, "tags": [{"text": "1иҝӣ2", "cls": "ladder-chip-cool muted-text"}, {"text": "ејәдё»зәҝ", "cls": "ladder-chip-strong red-text"}, {"text": "и·ҹйЈҺеӨҡж°ҹеӨҡ", "cls": "ladder-chip-warn orange-text"}, {"text": "жҷӢзә§з”ҹжҖҒејұ", "cls": "ladder-chip-warn orange-text"}, {"text": "й«ҳеәҰеҺӢеҲ¶", "cls": "ladder-chip-warn orange-text"}, {"text": "ж–ӯжқҝйЈҺйҷ©й«ҳ", "cls": "ladder-chip-warn orange-text"}, {"text": "жё©е’Ңж”ҫйҮҸ", "cls": "ladder-chip-cool muted-text"}, {"text": "жңӘејҖ", "cls": "ladder-chip-cool muted-text"}, {"text": "йҰ–е°Ғ09:47", "cls": "ladder-chip-cool muted-text"}, {"text": "йҮҸд»·е…ұжҢҜ", "cls": "ladder-chip-cool muted-text"}, {"text": "йўҳжқҗеҸ‘ж•Ј", "cls": "ladder-chip-cool muted-text"}, {"text": "е°ҒеҚ•3.56дәҝ", "cls": "ladder-chip-cool muted-text"}, {"text": "4.9%жҚўжүӢ", "cls": "ladder-chip-cool muted-text"}, {"text": "жҲҗдәӨйўқ20.71дәҝ", "cls": "ladder-chip-cool muted-text"}, {"text": "еёӮеҖј434дәҝ", "cls": "ladder-chip-cool muted-text"}, {"text": "жўҜйҳҹе®Ңж•ҙ", "cls": "ladder-chip-cool muted-text"}, {"text": "еҫ®еһӢз©ҝи¶Ҡ", "cls": "ladder-chip-cool muted-text"}, {"text": "йҰ–жқҝ", "cls": "ladder-chip-cool muted-text"}, {"text": "ж–°жқҗж–ҷ", "cls": "ladder-chip-cool muted-text"}, {"text": "дё“зІҫзү№ж–°", "cls": "ladder-chip-cool muted-text"}, {"text": "е®№йҮҸж ё", "cls": "ladder-chip-warn orange-text"}], "tagRows": [{"tone": "red", "tags": [{"text": "ејәдё»зәҝ", "cls": "ladder-chip-strong red-text"}]}, {"tone": "orange", "tags": [{"text": "и·ҹйЈҺеӨҡж°ҹеӨҡ", "cls": "ladder-chip-warn orange-text"}, {"text": "жҷӢзә§з”ҹжҖҒејұ", "cls": "ladder-chip-warn orange-text"}, {"text": "й«ҳеәҰеҺӢеҲ¶", "cls": "ladder-chip-warn orange-text"}, {"text": "ж–ӯжқҝйЈҺйҷ©й«ҳ", "cls": "ladder-chip-warn orange-text"}, {"text": "е®№йҮҸж ё", "cls": "ladder-chip-warn orange-text"}]}, {"tone": "muted", "tags": [{"text": "1иҝӣ2", "cls": "ladder-chip-cool muted-text"}, {"text": "жё©е’Ңж”ҫйҮҸ", "cls": "ladder-chip-cool muted-text"}, {"text": "жңӘејҖ", "cls": "ladder-chip-cool muted-text"}, {"text": "йҰ–е°Ғ09:47", "cls": "ladder-chip-cool muted-text"}, {"text": "йҮҸд»·е…ұжҢҜ", "cls": "ladder-chip-cool muted-text"}, {"text": "йўҳжқҗеҸ‘ж•Ј", "cls": "ladder-chip-cool muted-text"}, {"text": "е°ҒеҚ•3.56дәҝ", "cls": "ladder-chip-cool muted-text"}, {"text": "4.9%жҚўжүӢ", "cls": "ladder-chip-cool muted-text"}, {"text": "жҲҗдәӨйўқ20.71дәҝ", "cls": "ladder-chip-cool muted-text"}, {"text": "еёӮеҖј434дәҝ", "cls": "ladder-chip-cool muted-text"}, {"text": "жўҜйҳҹе®Ңж•ҙ", "cls": "ladder-chip-cool muted-text"}, {"text": "еҫ®еһӢз©ҝи¶Ҡ", "cls": "ladder-chip-cool muted-text"}, {"text": "йҰ–жқҝ", "cls": "ladder-chip-cool muted-text"}, {"text": "ж–°жқҗж–ҷ", "cls": "ladder-chip-cool muted-text"}, {"text": "дё“зІҫзү№ж–°", "cls": "ladder-chip-cool muted-text"}]}], "capacityLabel": "е®№йҮҸж ё", "reason": "<span class=\"reason-bits\">жўҜйҳҹи·ҹйҡҸ В· ејәдё»зәҝ В· йўҳжқҗжҢҒз»ӯ В· йўҳжқҗиҒ”еҠЁ В· жё©е’Ңж”ҫйҮҸ В· е°ҒжқҝзЁі В· е®№йҮҸеӨҹ В· й«ҳеәҰеҺӢеҲ¶ В· ж–ӯжқҝйЈҺйҷ©й«ҳ</span><div class=\"exp-wrap\"><div class=\"exp-row\"><span class=\"exp-pill pill-pre\">йў„жңҹ</span>дҪҺејҖпјҲ-4%~-1%%пјү+ з«һд»·йҮҸиғҪвүҘ0.93дәҝ</div><div class=\"exp-row\"><span class=\"exp-pill pill-hi\">и¶…йў„жңҹ</span>й«ҳејҖвүҘ-1%% + з«һд»·йҮҸиғҪвүҘ0.93дәҝ</div><div class=\"exp-row\"><span class=\"exp-pill pill-lo\">дҪҺйў„жңҹ</span>дҪҺдәҺ-4%% жҲ– з«һд»·йҮҸиғҪ<0.65дәҝ</div></div>", "factorRank": 16, "watchRank": 6, "watchGroup": "е®№йҮҸж ёеҝғ", "scoreLabel": "и§ӮеҜҹеӣ еӯҗ", "scoreSubLabel": "е®№йҮҸж ёеҝғ В· еҸӘи§ӮеҜҹ"}, {"name": "еҹғж–ҜйЎҝ", "code": "002747", "lbc": 2, "hy": "иҮӘеҠЁеҢ–и®ҫ", "fundYi": 4.99441973, "open": 2, "predTheme": "дё“зІҫзү№ж–°", "predThemeCanonical": "дё“зІҫзү№ж–°", "hasTier": true, "cjeYi": 20.1121104, "qualityLabel": "еёёи§„е°Ғжқҝ", "qualityScore": 68.0, "nextStep": "2иҝӣ3", "stepRate": 15.8, "stepContextScore": 44, "promoEcology": 22, "heightContextScore": 3, "environmentScore": 27, "leaderFactorScore": 73, "relayFactorScore": 53, "capacityFactorScore": 77, "riskControlScore": 30, "breakRisk": 90, "themePersistScore": 69, "leaderPhilosophyScore": 76, "recentHighSignal": {"available": false, "window": 7, "currentDate": "2026-06-30", "currentHigh": 37.33, "prevHigh": 39.8, "sampleSize": 5, "isRecentHigh": false, "breakoutPct": -6.21}, "thsNewhigh": {}, "themeLadderProfile": {"score": 45, "label": "дёӯдҪҚжүҝжҺҘ", "leaderBoards": 2, "coreCount": 3, "midCarryCount": 0, "followerCount": 8, "frontCount": 3, "gapCount": 0, "isComplete": false, "hasCarry": true, "leaderName": "еҹғж–ҜйЎҝ"}, "_isRecentHigh7d": false, "_breakoutDoubleConfirm": false, "leaderRole": "driver", "score": 54, "factorScore": 54, "factorBreakdown": {"environment": 27, "market": 39, "themeEnv": 100, "marketGate": -16, "sector": 64, "leader": 73, "relay": 53, "capacity": 77, "risk": 30, "opportunity": 81, "edge": 8, "heightBreakout": 0, "tide": 4}, "factorHint": "зҺҜеўғ27(дј‘жҒҜдјҳе…Ҳ) / жқҝеқ—64 / йҫҷеӨҙ73 / жҺҘеҠӣ53 / е®№йҮҸ77 / йЈҺйҷ©30 / жҪ®жұҗ+4 / жўҜйҳҹ45 / еҸӘи§ӮеҜҹ", "scoreBand": "еҸӘи§ӮеҜҹ", "scoreBandTone": "cool", "superLeaderTone": "", "scoreAction": "дёҚдё»еҠЁжҺҘеҠӣ", "marketGate": {"score": 27, "label": "дј‘жҒҜдјҳе…Ҳ", "action": "дёҚдё»еҠЁжҺҘеҠӣ"}, "sectorTrendScore": 70, "sectorRankScore": 83, "plateRank": 0, "plateName": "", "plateNameCanonical": "", "tideStatus": "observe_candidate", "tideAction": "watch", "tidePhase": "neutral", "tideCoreScore": 57.0, "tideEbbScore": 39.0, "tideAdjust": 4.0, "tideRelayAdjust": 1.0, "tideRiskAdjust": -4.0, "tideWatchAdjust": 12.0, "tideRelayGate": 3.0, "tideHint": "дё“зІҫзү№ж–°жңүи§ӮеҜҹд»·еҖјпјҢзӯүеҫ…жғ…з»Ә/йҮҸиғҪ/ж¶ҲжҒҜз»§з»ӯе…ұжҢҜгҖӮ", "tideCaution": "", "factorLabels": {"environment": "еҒҸејұ", "sector": "дёӯжҖ§", "leader": "еҒҸејә", "relay": "еҒҸејұ", "capacity": "еҒҸејә", "risk": "еҒҸејұ"}, "tags": [{"text": "2иҝӣ3", "cls": "ladder-chip-strong red-text"}, {"text": "2жқҝ", "cls": "ladder-chip-cool muted-text"}, {"text": "ејәдё»зәҝ", "cls": "ladder-chip-strong red-text"}, {"text": "ж ёеҝғжўҜйҳҹ", "cls": "ladder-chip-strong red-text"}, {"text": "еёҰеҠЁиңҖйҒ“иЈ…еӨҮгҖҒиӮҜзү№еӮ¬еҢ–", "cls": "ladder-chip-strong red-text"}, {"text": "жҷӢзә§з”ҹжҖҒејұ", "cls": "ladder-chip-warn orange-text"}, {"text": "й«ҳеәҰеҺӢеҲ¶", "cls": "ladder-chip-warn orange-text"}, {"text": "ж–ӯжқҝйЈҺйҷ©й«ҳ", "cls": "ladder-chip-warn orange-text"}, {"text": "2ж¬ЎејҖжқҝ", "cls": "ladder-chip-warn orange-text"}, {"text": "жё©е’Ңж”ҫйҮҸ", "cls": "ladder-chip-cool muted-text"}, {"text": "еёёи§„е°Ғжқҝ", "cls": "ladder-chip-cool muted-text"}, {"text": "йҰ–е°Ғ09:31", "cls": "ladder-chip-cool muted-text"}, {"text": "йҮҸд»·е…ұжҢҜ", "cls": "ladder-chip-cool muted-text"}, {"text": "йўҳжқҗеҸ‘ж•Ј", "cls": "ladder-chip-cool muted-text"}, {"text": "е°ҒеҚ•4.99дәҝ", "cls": "ladder-chip-cool muted-text"}, {"text": "6.3%жҚўжүӢ", "cls": "ladder-chip-cool muted-text"}, {"text": "жҲҗдәӨйўқ20.11дәҝ", "cls": "ladder-chip-cool muted-text"}, {"text": "еёӮеҖј397дәҝ", "cls": "ladder-chip-cool muted-text"}, {"text": "дёӯдҪҚжүҝжҺҘ", "cls": "ladder-chip-cool muted-text"}, {"text": "еҫ®еһӢз©ҝи¶Ҡ", "cls": "ladder-chip-cool muted-text"}, {"text": "дё“зІҫзү№ж–°", "cls": "ladder-chip-cool muted-text"}, {"text": "жҜ”дәҡиҝӘжҰӮеҝө", "cls": "ladder-chip-cool muted-text"}, {"text": "е®№йҮҸж ё", "cls": "ladder-chip-warn orange-text"}], "tagRows": [{"tone": "red", "tags": [{"text": "2иҝӣ3", "cls": "ladder-chip-strong red-text"}, {"text": "ејәдё»зәҝ", "cls": "ladder-chip-strong red-text"}, {"text": "ж ёеҝғжўҜйҳҹ", "cls": "ladder-chip-strong red-text"}, {"text": "еёҰеҠЁиңҖйҒ“иЈ…еӨҮгҖҒиӮҜзү№еӮ¬еҢ–", "cls": "ladder-chip-strong red-text"}]}, {"tone": "orange", "tags": [{"text": "жҷӢзә§з”ҹжҖҒејұ", "cls": "ladder-chip-warn orange-text"}, {"text": "й«ҳеәҰеҺӢеҲ¶", "cls": "ladder-chip-warn orange-text"}, {"text": "ж–ӯжқҝйЈҺйҷ©й«ҳ", "cls": "ladder-chip-warn orange-text"}, {"text": "2ж¬ЎејҖжқҝ", "cls": "ladder-chip-warn orange-text"}, {"text": "е®№йҮҸж ё", "cls": "ladder-chip-warn orange-text"}]}, {"tone": "muted", "tags": [{"text": "2жқҝ", "cls": "ladder-chip-cool muted-text"}, {"text": "жё©е’Ңж”ҫйҮҸ", "cls": "ladder-chip-cool muted-text"}, {"text": "еёёи§„е°Ғжқҝ", "cls": "ladder-chip-cool muted-text"}, {"text": "йҰ–е°Ғ09:31", "cls": "ladder-chip-cool muted-text"}, {"text": "йҮҸд»·е…ұжҢҜ", "cls": "ladder-chip-cool muted-text"}, {"text": "йўҳжқҗеҸ‘ж•Ј", "cls": "ladder-chip-cool muted-text"}, {"text": "е°ҒеҚ•4.99дәҝ", "cls": "ladder-chip-cool muted-text"}, {"text": "6.3%жҚўжүӢ", "cls": "ladder-chip-cool muted-text"}, {"text": "жҲҗдәӨйўқ20.11дәҝ", "cls": "ladder-chip-cool muted-text"}, {"text": "еёӮеҖј397дәҝ", "cls": "ladder-chip-cool muted-text"}, {"text": "дёӯдҪҚжүҝжҺҘ", "cls": "ladder-chip-cool muted-text"}, {"text": "еҫ®еһӢз©ҝи¶Ҡ", "cls": "ladder-chip-cool muted-text"}, {"text": "дё“зІҫзү№ж–°", "cls": "ladder-chip-cool muted-text"}, {"text": "жҜ”дәҡиҝӘжҰӮеҝө", "cls": "ladder-chip-cool muted-text"}]}], "capacityLabel": "е®№йҮҸж ё", "reason": "<span class=\"reason-bits\">дё“зІҫзү№ж–°йҫҷеӨҙеёҰеҠЁ В· жўҜйҳҹеёҰеҠЁиңҖйҒ“иЈ…еӨҮгҖҒиӮҜзү№еӮ¬еҢ– В· ејәдё»зәҝ В· йўҳжқҗжҢҒз»ӯ В· жё©е’Ңж”ҫйҮҸ В· ж—©е°Ғ В· е®№йҮҸеӨҹ В· й«ҳеәҰеҺӢеҲ¶ В· ж–ӯжқҝйЈҺйҷ©й«ҳ</span><div class=\"exp-wrap\"><div class=\"exp-row\"><span class=\"exp-pill pill-pre\">йў„жңҹ</span>дҪҺејҖпјҲ-2%~+0%%пјү+ з«һд»·йҮҸиғҪвүҘ0.91дәҝ</div><div class=\"exp-row\"><span class=\"exp-pill pill-hi\">и¶…йў„жңҹ</span>й«ҳејҖвүҘ+0%% + з«һд»·йҮҸиғҪвүҘ0.91дәҝ</div><div class=\"exp-row\"><span class=\"exp-pill pill-lo\">дҪҺйў„жңҹ</span>дҪҺдәҺ-2%% жҲ– з«һд»·йҮҸиғҪ<0.63дәҝ</div></div>", "factorRank": 3, "watchRank": 7, "watchGroup": "е®№йҮҸж ёеҝғ", "scoreLabel": "и§ӮеҜҹеӣ еӯҗ", "scoreSubLabel": "е®№йҮҸж ёеҝғ В· еҸӘи§ӮеҜҹ"}, {"name": "дёңж–№й”Ҷдёҡ", "code": "002167", "lbc": 2, "hy": "е°ҸйҮ‘еұһ", "fundYi": 3.85074754, "open": 2, "predTheme": "ж–°жқҗж–ҷ", "predThemeCanonical": "ж–°жқҗж–ҷ", "hasTier": true, "cjeYi": 13.55650144, "qualityLabel": "еёёи§„е°Ғжқҝ", "qualityScore": 68.0, "nextStep": "2иҝӣ3", "stepRate": 15.8, "stepContextScore": 44, "promoEcology": 22, "heightContextScore": 3, "environmentScore": 27, "leaderFactorScore": 59, "relayFactorScore": 56, "capacityFactorScore": 91, "riskControlScore": 30, "breakRisk": 90, "themePersistScore": 73, "leaderPhilosophyScore": 48, "recentHighSignal": {"available": false, "window": 7, "currentDate": "2026-06-30", "currentHigh": 22.07, "prevHigh": 23.06, "sampleSize": 5, "isRecentHigh": false, "breakoutPct": -4.29}, "thsNewhigh": {}, "themeLadderProfile": {"score": 77, "label": "жўҜйҳҹе®Ңж•ҙ", "leaderBoards": 3, "coreCount": 4, "midCarryCount": 3, "followerCount": 7, "frontCount": 4, "gapCount": 0, "isComplete": true, "hasCarry": true, "leaderName": "еӨҡж°ҹеӨҡ"}, "_isRecentHigh7d": false, "_breakoutDoubleConfirm": false, "leaderRole": "core", "score": 52, "factorScore": 52, "factorBreakdown": {"environment": 27, "market": 39, "themeEnv": 100, "marketGate": -16, "sector": 72, "leader": 59, "relay": 56, "capacity": 91, "risk": 30, "opportunity": 81, "edge": 5, "heightBreakout": 0, "tide": 4}, "factorHint": "зҺҜеўғ27(дј‘жҒҜдјҳе…Ҳ) / жқҝеқ—72 / йҫҷеӨҙ59 / жҺҘеҠӣ56 / е®№йҮҸ91 / йЈҺйҷ©30 / жҪ®жұҗ+4 / жўҜйҳҹ77 / еҸӘи§ӮеҜҹ", "scoreBand": "еҸӘи§ӮеҜҹ", "scoreBandTone": "cool", "superLeaderTone": "", "scoreAction": "дёҚдё»еҠЁжҺҘеҠӣ", "marketGate": {"score": 27, "label": "дј‘жҒҜдјҳе…Ҳ", "action": "дёҚдё»еҠЁжҺҘеҠӣ"}, "sectorTrendScore": 75, "sectorRankScore": 88, "plateRank": 0, "plateName": "", "plateNameCanonical": "", "tideStatus": "observe_candidate", "tideAction": "watch", "tidePhase": "neutral", "tideCoreScore": 58.0, "tideEbbScore": 39.0, "tideAdjust": 4.0, "tideRelayAdjust": 1.0, "tideRiskAdjust": -4.0, "tideWatchAdjust": 12.0, "tideRelayGate": 3.0, "tideHint": "ж–°жқҗж–ҷжңүи§ӮеҜҹд»·еҖјпјҢзӯүеҫ…жғ…з»Ә/йҮҸиғҪ/ж¶ҲжҒҜз»§з»ӯе…ұжҢҜгҖӮ", "tideCaution": "", "factorLabels": {"environment": "еҒҸејұ", "sector": "еҒҸејә", "leader": "дёӯжҖ§", "relay": "еҒҸејұ", "capacity": "ејә", "risk": "еҒҸејұ"}, "tags": [{"text": "2иҝӣ3", "cls": "ladder-chip-strong red-text"}, {"text": "2жқҝ", "cls": "ladder-chip-cool muted-text"}, {"text": "ејәдё»зәҝ", "cls": "ladder-chip-strong red-text"}, {"text": "ж ёеҝғжўҜйҳҹ", "cls": "ladder-chip-strong red-text"}, {"text": "и·ҹйЈҺеӨҡж°ҹеӨҡ", "cls": "ladder-chip-warn orange-text"}, {"text": "жҷӢзә§з”ҹжҖҒејұ", "cls": "ladder-chip-warn orange-text"}, {"text": "й«ҳеәҰеҺӢеҲ¶", "cls": "ladder-chip-warn orange-text"}, {"text": "ж–ӯжқҝйЈҺйҷ©й«ҳ", "cls": "ladder-chip-warn orange-text"}, {"text": "2ж¬ЎејҖжқҝ", "cls": "ladder-chip-warn orange-text"}, {"text": "жё©е’Ңж”ҫйҮҸ", "cls": "ladder-chip-cool muted-text"}, {"text": "еёёи§„е°Ғжқҝ", "cls": "ladder-chip-cool muted-text"}, {"text": "йҰ–е°Ғ09:32", "cls": "ladder-chip-cool muted-text"}, {"text": "йҮҸд»·е…ұжҢҜ", "cls": "ladder-chip-cool muted-text"}, {"text": "йўҳжқҗеҸ‘ж•Ј", "cls": "ladder-chip-cool muted-text"}, {"text": "е°ҒеҚ•3.85дәҝ", "cls": "ladder-chip-cool muted-text"}, {"text": "7.5%жҚўжүӢ", "cls": "ladder-chip-cool muted-text"}, {"text": "жҲҗдәӨйўқ13.56дәҝ", "cls": "ladder-chip-cool muted-text"}, {"text": "еёӮеҖј188дәҝ", "cls": "ladder-chip-cool muted-text"}, {"text": "жўҜйҳҹе®Ңж•ҙ", "cls": "ladder-chip-cool muted-text"}, {"text": "еҫ®еһӢз©ҝи¶Ҡ", "cls": "ladder-chip-cool muted-text"}, {"text": "ж–°жқҗж–ҷ", "cls": "ladder-chip-cool muted-text"}, {"text": "й”Ӯз”өжұ ", "cls": "ladder-chip-cool muted-text"}, {"text": "е®№йҮҸж ё", "cls": "ladder-chip-warn orange-text"}], "tagRows": [{"tone": "red", "tags": [{"text": "2иҝӣ3", "cls": "ladder-chip-strong red-text"}, {"text": "ејәдё»зәҝ", "cls": "ladder-chip-strong red-text"}, {"text": "ж ёеҝғжўҜйҳҹ", "cls": "ladder-chip-strong red-text"}]}, {"tone": "orange", "tags": [{"text": "и·ҹйЈҺеӨҡж°ҹеӨҡ", "cls": "ladder-chip-warn orange-text"}, {"text": "жҷӢзә§з”ҹжҖҒејұ", "cls": "ladder-chip-warn orange-text"}, {"text": "й«ҳеәҰеҺӢеҲ¶", "cls": "ladder-chip-warn orange-text"}, {"text": "ж–ӯжқҝйЈҺйҷ©й«ҳ", "cls": "ladder-chip-warn orange-text"}, {"text": "2ж¬ЎејҖжқҝ", "cls": "ladder-chip-warn orange-text"}, {"text": "е®№йҮҸж ё", "cls": "ladder-chip-warn orange-text"}]}, {"tone": "muted", "tags": [{"text": "2жқҝ", "cls": "ladder-chip-cool muted-text"}, {"text": "жё©е’Ңж”ҫйҮҸ", "cls": "ladder-chip-cool muted-text"}, {"text": "еёёи§„е°Ғжқҝ", "cls": "ladder-chip-cool muted-text"}, {"text": "йҰ–е°Ғ09:32", "cls": "ladder-chip-cool muted-text"}, {"text": "йҮҸд»·е…ұжҢҜ", "cls": "ladder-chip-cool muted-text"}, {"text": "йўҳжқҗеҸ‘ж•Ј", "cls": "ladder-chip-cool muted-text"}, {"text": "е°ҒеҚ•3.85дәҝ", "cls": "ladder-chip-cool muted-text"}, {"text": "7.5%жҚўжүӢ", "cls": "ladder-chip-cool muted-text"}, {"text": "жҲҗдәӨйўқ13.56дәҝ", "cls": "ladder-chip-cool muted-text"}, {"text": "еёӮеҖј188дәҝ", "cls": "ladder-chip-cool muted-text"}, {"text": "жўҜйҳҹе®Ңж•ҙ", "cls": "ladder-chip-cool muted-text"}, {"text": "еҫ®еһӢз©ҝи¶Ҡ", "cls": "ladder-chip-cool muted-text"}, {"text": "ж–°жқҗж–ҷ", "cls": "ladder-chip-cool muted-text"}, {"text": "й”Ӯз”өжұ ", "cls": "ladder-chip-cool muted-text"}]}], "capacityLabel": "е®№йҮҸж ё", "reason": "<span class=\"reason-bits\">ж ёеҝғжўҜйҳҹ В· жўҜйҳҹи·ҹйҡҸ В· ејәдё»зәҝ В· йўҳжқҗжҢҒз»ӯ В· жё©е’Ңж”ҫйҮҸ В· ж—©е°Ғ В· е®№йҮҸеӨҹ В· й«ҳеәҰеҺӢеҲ¶ В· ж–ӯжқҝйЈҺйҷ©й«ҳ</span><div class=\"exp-wrap\"><div class=\"exp-row\"><span class=\"exp-pill pill-pre\">йў„жңҹ</span>дҪҺејҖпјҲ-2%~+0%%пјү+ з«һд»·йҮҸиғҪвүҘ0.61дәҝ</div><div class=\"exp-row\"><span class=\"exp-pill pill-hi\">и¶…йў„жңҹ</span>й«ҳејҖвүҘ+0%% + з«һд»·йҮҸиғҪвүҘ0.61дәҝ</div><div class=\"exp-row\"><span class=\"exp-pill pill-lo\">дҪҺйў„жңҹ</span>дҪҺдәҺ-2%% жҲ– з«һд»·йҮҸиғҪ<0.43дәҝ</div></div>", "factorRank": 4, "watchRank": 8, "watchGroup": "е®№йҮҸж ёеҝғ", "scoreLabel": "и§ӮеҜҹеӣ еӯҗ", "scoreSubLabel": "е®№йҮҸж ёеҝғ В· еҸӘи§ӮеҜҹ"}], "relaySelectionMode": "broad", "relayDiagnostics": {"scored": 82, "themeRows": 43, "heightBreakoutEligible": 0, "coreEligible": 0, "highMarkEligible": 0, "oneToTwoEligible": 0, "relaxedEligible": 0, "broadEligible": 2, "emergencyEligible": 10, "riskBlocked": 82, "openBlocked": 2, "stepWeak": 60, "yiziBlocked": 6, "shrinkBlocked": 20, "tideBlocked": 0}, "watchGroups": ["й«ҳдҪҚеҲҶжӯ§", "е®№йҮҸж ёеҝғ", "е®№йҮҸж ёеҝғ", "е®№йҮҸж ёеҝғ", "е®№йҮҸж ёеҝғ", "е®№йҮҸж ёеҝғ", "е®№йҮҸж ёеҝғ", "е®№йҮҸж ёеҝғ"]}